Metadata-Version: 2.1
Name: mlflow-oss-artifact
Version: 2.0.0
Summary: Plugin that provides Aliyun oss Artifact Store functionality for MLflow
Home-page: https://github.com/mrly16/mlflow-aliyunstore/archive/refs/tags/2.0.0.tar.gz
Author: Liangyi Murong
Author-email: mrly@xkool.org
License: Apache License 2.0
Platform: UNKNOWN
